MANIFEST.in
README.md
requirements.txt
setup.py
include/metal/decomposer.hpp
include/metal/macros.h
include/metal/unit.h
include/metal/gdb/core.h
include/metal/gdb/unit.h
include/metal/hosted/unit.h
include/metal/serial/argv.h
include/metal/serial/core.h
include/metal/serial/syscalls.h
include/metal/serial/unit.h
metal/flags.py
metal/newlib.py
metal/unit.py
metal/../include/metal/decomposer.hpp
metal/../include/metal/macros.h
metal/../include/metal/unit.h
metal/../include/metal/gdb/core.h
metal/../include/metal/gdb/unit.h
metal/../include/metal/hosted/unit.h
metal/../include/metal/serial/argv.h
metal/../include/metal/serial/core.h
metal/../include/metal/serial/syscalls.h
metal/../include/metal/serial/unit.h
metal/../src/metal/gdb/syscalls.c
metal/../src/metal/serial/syscalls.c
metal/gdb/__init__.py
metal/gdb/argv.py
metal/gdb/default.py
metal/gdb/exitcode.py
metal/gdb/metal_break.py
metal/gdb/newlib.py
metal/gdb/timeout.py
metal/gdb/unit.py
metal/serial/__init__.py
metal/serial/argv.py
metal/serial/default_hooks.py
metal/serial/elfreader.py
metal/serial/engine.py
metal/serial/generate.py
metal/serial/hooks.py
metal/serial/interpret.py
metal/serial/location.py
metal/serial/newlib.py
metal/serial/preprocessor.py
metal/serial/read_symbols.py
metal/serial/unit.py
metal_test.egg-info/PKG-INFO
metal_test.egg-info/SOURCES.txt
metal_test.egg-info/dependency_links.txt
metal_test.egg-info/entry_points.txt
metal_test.egg-info/requires.txt
metal_test.egg-info/top_level.txt
src/metal/gdb/syscalls.c
src/metal/serial/syscalls.c