Metadata-Version: 2.1
Name: metal-test
Version: 0.2.2
Summary: A C/C++ toolset for bare metal & embedded developments
Home-page: http://pypi.python.org/pypi/metal_test
Author: Klemens Morgenstern
Author-email: klemens@metal.ci
License: APACHE
Platform: UNKNOWN
Classifier: Intended Audience :: Developers
Classifier: Topic :: Software Development :: Embedded Systems
Classifier: License :: OSI Approved :: Apache Software License
Classifier: Programming Language :: Python :: 3
